pottery/__init__.py
pottery/aionextid.py
pottery/aioredlock.py
pottery/annotations.py
pottery/base.py
pottery/bloom.py
pottery/cache.py
pottery/counter.py
pottery/deque.py
pottery/dict.py
pottery/exceptions.py
pottery/executor.py
pottery/hyper.py
pottery/list.py
pottery/monkey.py
pottery/nextid.py
pottery/py.typed
pottery/queue.py
pottery/redlock.py
pottery/set.py
pottery/timer.py
pottery-3.0.1.dist-info/licenses/LICENSE
pottery-3.0.1.dist-info/METADATA
pottery-3.0.1.dist-info/WHEEL
pottery-3.0.1.dist-info/top_level.txt
pottery-3.0.1.dist-info/RECORD
