Metadata-Version: 2.4
Name: pottery
Version: 3.0.1
Summary: Redis for Humans.
Home-page: https://github.com/brainix/pottery
Author: Rajiv Bakulesh Shah
Author-email: brainix@gmail.com
Keywords: Redis client persistent storage
Classifier: Intended Audience :: Developers
Classifier: Development Status :: 4 - Beta
Classifier: Topic :: Database :: Front-Ends
Classifier: Topic :: System :: Distributed Computing
Classifier: Topic :: Utilities
Classifier: Programming Language :: Python :: 3 :: Only
Classifier: Programming Language :: Python :: 3.9
Classifier: Programming Language :: Python :: 3.10
Classifier: Programming Language :: Python :: 3.11
Classifier: Programming Language :: Python :: 3.12
Classifier: Programming Language :: Python :: 3.13
Classifier: Framework :: AsyncIO
Classifier: Typing :: Typed
Requires-Python: >=3.9, <4
License-File: LICENSE
Requires-Dist: redis>=4.2.0rc1
Requires-Dist: mmh3
Requires-Dist: typing_extensions
Dynamic: author
Dynamic: author-email
Dynamic: classifier
Dynamic: description
Dynamic: description-content-type
Dynamic: home-page
Dynamic: keywords
Dynamic: license-file
Dynamic: requires-dist
Dynamic: requires-python
Dynamic: summary
